apitest_ezgo/Compare.py
apitest_ezgo/DbHelper.py
apitest_ezgo/FastRequest.py
apitest_ezgo/__about__.py
apitest_ezgo/__init__.py
apitest_ezgo/compat.py
apitest_ezgo/Har2Template/__init__.py
apitest_ezgo/Har2Template/cli.py
apitest_ezgo/Har2Template/core.py
apitest_ezgo/Har2Template/utils.py
apitest_ezgo-2.0.4.dist-info/METADATA
apitest_ezgo-2.0.4.dist-info/WHEEL
apitest_ezgo-2.0.4.dist-info/entry_points.txt
apitest_ezgo-2.0.4.dist-info/top_level.txt
apitest_ezgo-2.0.4.dist-info/RECORD
