Metadata-Version: 2.1
Name: apitest-ezgo
Version: 2.0.4
Summary: easy http interface test frame
Home-page: https://github.com/gawen-ma/ezauto
Author: Gawen
Author-email: 502286126@qq.com
License: MIT
Platform: UNKNOWN
Classifier: License :: OSI Approved :: MIT License
Classifier: Operating System :: OS Independent
Requires-Python: >=2.7
Requires-Dist: jsonpath
Requires-Dist: DBUtils (==1.3)
Requires-Dist: deepdiff
Requires-Dist: jsonpath-ng
Requires-Dist: tabulate
Requires-Dist: requests-toolbelt
